helios_controller/__init__.py
helios_controller/helios.py
helios_controller/utilities.py
helios_controller-0.1.0.dist-info/METADATA
helios_controller-0.1.0.dist-info/WHEEL
helios_controller-0.1.0.dist-info/RECORD
