Metadata-Version: 2.1
Name: helios_controller
Version: 0.1.0
Summary: 
Author: Tucker Downs
Author-email: tucker@roevisual.us
Requires-Python: >=3.9,<4.0
Classifier: Programming Language :: Python :: 3
Classifier: Programming Language :: Python :: 3.9
Classifier: Programming Language :: Python :: 3.10
Classifier: Programming Language :: Python :: 3.11
Requires-Dist: requests (>=2.31.0,<3.0.0)
